elastic2_doc_manager_unset_fix-1.0.0.dist-info/METADATA
elastic2_doc_manager_unset_fix-1.0.0.dist-info/RECORD
elastic2_doc_manager_unset_fix-1.0.0.dist-info/WHEEL
elastic2_doc_manager_unset_fix-1.0.0.dist-info/top_level.txt
mongo_connector/__init__.py
mongo_connector/doc_managers/__init__.py
mongo_connector/doc_managers/elastic2_doc_manager.py
